{"cameraMode":{"drawMode":0,"name":"Shaded","section":"Shading Mode"},"sceneLighting":true,"audioPlay":false,"sceneViewState":{"m_AlwaysRefresh":false,"showFog":true,"showSkybox":true,"showFlares":true,"showImageEffects":true,"showParticleSystems":true,"showVisualEffectGraphs":true,"m_FxEnabled":true},"in2DMode":false,"pivot":{"x":-0.5807090401649475,"y":2.4788851737976076,"z":-3.867959499359131},"rotation":{"x":-0.07319395989179611,"y":0.1214628517627716,"z":-0.00898186955600977,"w":-0.9898586273193359},"size":10.0,"orthographic":false}